pybob/GeoImg.py
pybob/ICESat.py
pybob/VelField.py
pybob/__init__.py
pybob/bob_tools.py
pybob/continuity_tools.py
pybob/coreg_tools.py
pybob/ddem_tools.py
pybob/hexagon_tools.py
pybob/image_tools.py
pybob/landsat_tools.py
pybob/plot_tools.py
pybob/tools/calculate_mmaster_dh_curves.py
pybob/tools/convert_elevations.py
pybob/tools/dem_coregistration.py
pybob/tools/dem_coregistration_grid.py
pybob/tools/dem_difference.py
pybob/tools/extract_ICESat.py
pybob/tools/find_aster_dem_pairs.py
pybob/tools/generate_panchromatic.py
pybob/tools/image_footprint.py
pybob/tools/image_footprint_from_met.py
pybob/tools/orthorectify_landsat.py
pybob/tools/register_landsat.py
pybob/tools/write_utm_zones.py
pybob-0.26.2.dist-info/LICENSE
pybob-0.26.2.dist-info/METADATA
pybob-0.26.2.dist-info/WHEEL
pybob-0.26.2.dist-info/top_level.txt
pybob-0.26.2.dist-info/RECORD
